chrome_extension_generator/__init__.py
chrome_extension_generator/_modidx.py
chrome_extension_generator/core.py
chrome_extension_generator-0.0.6.dist-info/LICENSE
chrome_extension_generator-0.0.6.dist-info/METADATA
chrome_extension_generator-0.0.6.dist-info/WHEEL
chrome_extension_generator-0.0.6.dist-info/entry_points.txt
chrome_extension_generator-0.0.6.dist-info/top_level.txt
chrome_extension_generator-0.0.6.dist-info/RECORD
